Workbook

Sheet Summary
A1: Medicare Inpatient: Pricing, Payment & Documentation Opportunity (DY2023)
A3: Headline KPI | B3: Value
A4: Total charges (list price) | B4: =Assumptions!B13
A5: Total payments (all payers) | B5: =Assumptions!B14
A6: Payment-to-charge ratio | B6: =Assumptions!B14/Assumptions!B13
A7: Charge-to-payment gap (descriptive only) | B7: =Assumptions!B16
A8: Hospitals screened for severity mix | B8: =Scenarios!C9
A9: Eligible for documentation review | B9: =Scenarios!B9
A11: Documentation-capture opportunity | B11: Low | C11: Base | D11: High
A12: =Scenarios!A5 | B12: =Scenarios!D5 | C12: =Scenarios!E5 | D12: =Scenarios!F5
A13: =Scenarios!A6 | B13: =Scenarios!D6 | C13: =Scenarios!E6 | D13: =Scenarios!F6
A14: =Scenarios!A7 | B14: =Scenarios!D7 | C14: =Scenarios!E7 | D14: =Scenarios!F7
A16: Read the Assumptions sheet before quoting any number. See v1_Reconciliation for corrections to the earlier model.

Sheet Assumptions
A1: Assumptions (blue cells are inputs - change them and every sheet recalculates)
A3: Input | B3: Value | C3: Notes
A4: Review threshold: minimum shortfall vs peers (% of expected payment) | B4: 0.02 | C4: Only hospitals at least this far below peers' severity mix are counted. Filters statistical noise.
A5: Capture rate - Low | B5: 0.1 | C5: Share of the shortfall realistically supported by clinical documentation review
A6: Capture rate - Base | B6: 0.25
A7: Capture rate - High | B7: 0.5
A8: Scope A: top N hospitals reviewed | B8: 25 | C8: Pilot wave: largest shortfalls first
A9: Scope B: top N hospitals reviewed | B9: 100 | C9: Programme wave
A10: Scope C: top N hospitals reviewed | B10: 10000 | C10: All eligible hospitals (N larger than the list)
A12: Fixed facts (from the SQL views, not editable)
A13: Total charges, all hospitals | B13: 4.3216929e+11
A14: Total payments, all payers | B14: 8.84111e+10
A15: of which Medicare | B15: 7.3392759e+10
A16: Charge-to-payment gap (descriptive, NOT recoverable) | B16: 3.4375819e+11
A17: Discharges | B17: 4960325
A19: Source: CMS Medicare Inpatient Hospitals by Provider and Service, data year 2023 (fee-for-service Medicare only; cells of 10 or fewer discharges suppressed).

Sheet Hospital_Screen
A1: Provider ID | B1: Hospital | C1: State | D1: Setting | E1: Tiered discharges | F1: Top-tier share | G1: Peer expected share | H1: Expected payment ($) | I1: Severity shortfall ($) | J1: Shortfall % | K1: Eligible (1/0) | L1: Eligible shortfall ($) | M1: Eligible rank
A2: 100087 | B2: Sarasota Memorial Hospital | C2: FL | D2: Metropolitan | E2: 14547 | F2: 0.4319791 | G2: 0.48097131 | H2: 2.6135616e+08 | I2: 8167292.3 | J2: 0.031249664 | K2: =IF(AND(I2>0,J2>=Assumptions!$B$4),1,0) | L2: =I2*K2 | M2: =SUM($K$2:K2)
A3: 330182 | B3: St Francis Hospital, Roslyn | C3: NY | D3: Metropolitan | E3: 8495 | F3: 0.43307828 | G3: 0.5277774 | H3: 1.6540995e+08 | I3: 7959610.1 | J3: 0.048120505 | K3: =IF(AND(I3>0,J3>=Assumptions!$B$4),1,0) | L3: =I3*K3 | M3: =SUM($K$2:K3)
A4: 100088 | B4: Baptist Medical Center Jacksonville | C4: FL | D4: Metropolitan | E4: 10800 | F4: 0.46638889 | G4: 0.51498118 | H4: 1.873506e+08 | I4: 7598158.2 | J4: 0.040555825 | K4: =IF(AND(I4>0,J4>=Assumptions!$B$4),1,0) | L4: =I4*K4 | M4: =SUM($K$2:K4)
A5: 080001 | B5: Christianacare | C5: DE | D5: Metropolitan | E5: 14353 | F5: 0.47523166 | G5: 0.51270237 | H5: 2.4985941e+08 | I5: 6739790.7 | J5: 0.026974332 | K5: =IF(AND(I5>0,J5>=Assumptions!$B$4),1,0) | L5: =I5*K5 | M5: =SUM($K$2:K5)
A6: 050224 | B6: Hoag Memorial Hospital Presbyterian | C6: CA | D6: Metropolitan | E6: 7138 | F6: 0.47814514 | G6: 0.55630214 | H6: 1.2270266e+08 | I6: 6337103.4 | J6: 0.051646017 | K6: =IF(AND(I6>0,J6>=Assumptions!$B$4),1,0) | L6: =I6*K6 | M6: =SUM($K$2:K6)
A7: 310022 | B7: West Jersey Hospital | C7: NJ | D7: Metropolitan | E7: 6959 | F7: 0.43195861 | G7: 0.54610567 | H7: 94936293 | I7: 5468314.4 | J7: 0.05759983 | K7: =IF(AND(I7>0,J7>=Assumptions!$B$4),1,0) | L7: =I7*K7 | M7: =SUM($K$2:K7)
A8: 220077 | B8: Baystate Medical Center | C8: MA | D8: Metropolitan | E8: 8941 | F8: 0.50274019 | G8: 0.55411784 | H8: 1.5755115e+08 | I8: 5448176.3 | J8: 0.034580364 | K8: =IF(AND(I8>0,J8>=Assumptions!$B$4),1,0) | L8: =I8*K8 | M8: =SUM($K$2:K8)
A9: 210023 | B9: Luminis Health Anne Arundel Medical Center, Inc | C9: MD | D9: Metropolitan | E9: 6647 | F9: 0.47239356 | G9: 0.56281416 | H9: 99012530 | I9: 5367128.9 | J9: 0.054206563 | K9: =IF(AND(I9>0,J9>=Assumptions!$B$4),1,0) | L9: =I9*K9 | M9: =SUM($K$2:K9)
A10: 420007 | B10: Spartanburg Medical Center | C10: SC | D10: Metropolitan | E10: 5011 | F10: 0.40251447 | G10: 0.50744704 | H10: 83463639 | I10: 5312484.7 | J10: 0.063650288 | K10: =IF(AND(I10>0,J10>=Assumptions!$B$4),1,0) | L10: =I10*K10 | M10: =SUM($K$2:K10)
A11: 140148 | B11: Memorial Medical Center | C11: IL | D11: Metropolitan | E11: 4036 | F11: 0.4370664 | G11: 0.53000856 | H11: 70691123 | I11: 5110146.4 | J11: 0.072288376 | K11: =IF(AND(I11>0,J11>=Assumptions!$B$4),1,0) | L11: =I11*K11 | M11: =SUM($K$2:K11)
A12: 330393 | B12: Stony Brook University Hospital | C12: NY | D12: Metropolitan | E12: 10472 | F12: 0.47832315 | G12: 0.52275659 | H12: 1.7486264e+08 | I12: 4989751 | J12: 0.028535262 | K12: =IF(AND(I12>0,J12>=Assumptions!$B$4),1,0) | L12: =I12*K12 | M12: =SUM($K$2:K12)
A13: 010039 | B13: Huntsville Hospital | C13: AL | D13: Metropolitan | E13: 8096 | F13: 0.47443182 | G13: 0.51786044 | H13: 1.4945993e+08 | I13: 4776255 | J13: 0.03195676 | K13: =IF(AND(I13>0,J13>=Assumptions!$B$4),1,0) | L13: =I13*K13 | M13: =SUM($K$2:K13)
... A1997: 330214 | B1997: Nyu Langone Hospitals | C1997: NY | D1997: Metropolitan | E1997: 21873 | F1997: 0.56334293 | G1997: 0.51313018 | H1997: 4.1086756e+08 | I1997: -17203342 | J1997: -0.041870771 | K1997: =IF(AND(I1997>0,J1997>=Assumptions!$B$4),1,0) | L1997: =I1997*K1997 | M1997: =SUM($K$2:K1997)

Sheet Scenarios
A1: Documentation-capture opportunity: annual payment effect, all payers on Medicare cases
A2: Eligible shortfall x capture rate. A screen for clinical review - not a revenue forecast.
A4: Scope | B4: Hospitals in scope | C4: Eligible shortfall ($) | D4: Low | E4: Base | F4: High
A5: ="A. Pilot (top "&TEXT(MIN(Assumptions!$B$8,MAX(Hospital_Screen!$M$2:$M$1997)),"#,##0")&" hospitals)" | B5: =MIN(Assumptions!$B$8,MAX(Hospital_Screen!$M$2:$M$1997)) | C5: =SUMIFS(Hospital_Screen!$L$2:$L$1997,Hospital_Screen!$M$2:$M$1997,"<="&Assumptions!$B$8) | D5: =$C5*Assumptions!$B$5 | E5: =$C5*Assumptions!$B$6 | F5: =$C5*Assumptions!$B$7
A6: ="B. Programme (top "&TEXT(MIN(Assumptions!$B$9,MAX(Hospital_Screen!$M$2:$M$1997)),"#,##0")&" hospitals)" | B6: =MIN(Assumptions!$B$9,MAX(Hospital_Screen!$M$2:$M$1997)) | C6: =SUMIFS(Hospital_Screen!$L$2:$L$1997,Hospital_Screen!$M$2:$M$1997,"<="&Assumptions!$B$9) | D6: =$C6*Assumptions!$B$5 | E6: =$C6*Assumptions!$B$6 | F6: =$C6*Assumptions!$B$7
A7: ="C. All eligible (top "&TEXT(MIN(Assumptions!$B$10,MAX(Hospital_Screen!$M$2:$M$1997)),"#,##0")&" hospitals)" | B7: =MIN(Assumptions!$B$10,MAX(Hospital_Screen!$M$2:$M$1997)) | C7: =SUMIFS(Hospital_Screen!$L$2:$L$1997,Hospital_Screen!$M$2:$M$1997,"<="&Assumptions!$B$10) | D7: =$C7*Assumptions!$B$5 | E7: =$C7*Assumptions!$B$6 | F7: =$C7*Assumptions!$B$7
A9: Eligible hospitals / total screened | B9: =MAX(Hospital_Screen!$M$2:$M$1997) | C9: =COUNT(Hospital_Screen!$I$2:$I$1997)
A10: Eligible shortfall as % of expected payments on tiered DRGs | C10: =SUMIFS(Hospital_Screen!$L$2:$L$1997,Hospital_Screen!$M$2:$M$1997,">0")/SUM(Hospital_Screen!$H$2:$H$1997)
A13: Sensitivity: all hospitals at or above the threshold, by capture rate
A14: Capture rate \ review threshold | B14: 0 | C14: 0.01 | D14: 0.02 | E14: 0.03 | F14: 0.05
A15: 0.05 | B15: =SUMIFS(Hospital_Screen!$I$2:$I$1997,Hospital_Screen!$J$2:$J$1997,">="&B$14,Hospital_Screen!$I$2:$I$1997,">0")*$A15 | C15: =SUMIFS(Hospital_Screen!$I$2:$I$1997,Hospital_Screen!$J$2:$J$1997,">="&C$14,Hospital_Screen!$I$2:$I$1997,">0")*$A15 | D15: =SUMIFS(Hospital_Screen!$I$2:$I$1997,Hospital_Screen!$J$2:$J$1997,">="&D$14,Hospital_Screen!$I$2:$I$1997,">0")*$A15 | E15: =SUMIFS(Hospital_Screen!$I$2:$I$1997,Hospital_Screen!$J$2:$J$1997,">="&E$14,Hospital_Screen!$I$2:$I$1997,">0")*$A15 | F15: =SUMIFS(Hospital_Screen!$I$2:$I$1997,Hospital_Screen!$J$2:$J$1997,">="&F$14,Hospital_Screen!$I$2:$I$1997,">0")*$A15
A16: 0.1 | B16: =SUMIFS(Hospital_Screen!$I$2:$I$1997,Hospital_Screen!$J$2:$J$1997,">="&B$14,Hospital_Screen!$I$2:$I$1997,">0")*$A16 | C16: =SUMIFS(Hospital_Screen!$I$2:$I$1997,Hospital_Screen!$J$2:$J$1997,">="&C$14,Hospital_Screen!$I$2:$I$1997,">0")*$A16 | D16: =SUMIFS(Hospital_Screen!$I$2:$I$1997,Hospital_Screen!$J$2:$J$1997,">="&D$14,Hospital_Screen!$I$2:$I$1997,">0")*$A16 | E16: =SUMIFS(Hospital_Screen!$I$2:$I$1997,Hospital_Screen!$J$2:$J$1997,">="&E$14,Hospital_Screen!$I$2:$I$1997,">0")*$A16 | F16: =SUMIFS(Hospital_Screen!$I$2:$I$1997,Hospital_Screen!$J$2:$J$1997,">="&F$14,Hospital_Screen!$I$2:$I$1997,">0")*$A16
A17: 0.25 | B17: =SUMIFS(Hospital_Screen!$I$2:$I$1997,Hospital_Screen!$J$2:$J$1997,">="&B$14,Hospital_Screen!$I$2:$I$1997,">0")*$A17 | C17: =SUMIFS(Hospital_Screen!$I$2:$I$1997,Hospital_Screen!$J$2:$J$1997,">="&C$14,Hospital_Screen!$I$2:$I$1997,">0")*$A17 | D17: =SUMIFS(Hospital_Screen!$I$2:$I$1997,Hospital_Screen!$J$2:$J$1997,">="&D$14,Hospital_Screen!$I$2:$I$1997,">0")*$A17 | E17: =SUMIFS(Hospital_Screen!$I$2:$I$1997,Hospital_Screen!$J$2:$J$1997,">="&E$14,Hospital_Screen!$I$2:$I$1997,">0")*$A17 | F17: =SUMIFS(Hospital_Screen!$I$2:$I$1997,Hospital_Screen!$J$2:$J$1997,">="&F$14,Hospital_Screen!$I$2:$I$1997,">0")*$A17
A18: 0.5 | B18: =SUMIFS(Hospital_Screen!$I$2:$I$1997,Hospital_Screen!$J$2:$J$1997,">="&B$14,Hospital_Screen!$I$2:$I$1997,">0")*$A18 | C18: =SUMIFS(Hospital_Screen!$I$2:$I$1997,Hospital_Screen!$J$2:$J$1997,">="&C$14,Hospital_Screen!$I$2:$I$1997,">0")*$A18 | D18: =SUMIFS(Hospital_Screen!$I$2:$I$1997,Hospital_Screen!$J$2:$J$1997,">="&D$14,Hospital_Screen!$I$2:$I$1997,">0")*$A18 | E18: =SUMIFS(Hospital_Screen!$I$2:$I$1997,Hospital_Screen!$J$2:$J$1997,">="&E$14,Hospital_Screen!$I$2:$I$1997,">0")*$A18 | F18: =SUMIFS(Hospital_Screen!$I$2:$I$1997,Hospital_Screen!$J$2:$J$1997,">="&F$14,Hospital_Screen!$I$2:$I$1997,">0")*$A18
A21: Cross-check: same figures computed in Python from the SQL view (should equal the Base column and the 2% / 25% sensitivity cell)
A22: Scope | B22: Python (Base 25%) | C22: Excel (Base) | D22: Difference
A23: A | B23: 31331555 | C23: =E5 | D23: =C23-B23
A24: B | B24: 75407008 | C24: =E6 | D24: =C24-B24
A25: C | B25: 1.3874824e+08 | C25: =E7 | D25: =C25-B25

Sheet v1_Reconciliation
A1: What changed from v1 of this model, and why
A3: v1 figure | B3: v1 value | C3: Corrected / retired | D3: Cause
A4: Total 'revenue gap' | B4: 717550000000 | C4: 3.4375819e+11 | D4: v1 summed an entire pivot-table column, including its Grand Total row, so every dollar counted twice ($358.8B on Medicare payment). v2 uses all-payer payment: $343.8B.
A5: 'Top DRG optimisation' (8%) | B5: 57400000000 | C5: 8990000000 | D5: v1 applied 8% to the whole gap, not the top 10 DRGs (31% of the gap). Correct v1 logic = 8% x $112.5B.
A6: 'Top 20 providers' (10%) | B6: 236000000 | C6: 4650000000 | D6: v1 summed the first 20 rows of an unsorted pivot, not the largest 20. Correct v1 logic = 10% x $46.5B.
A7: '5% efficiency gain' | B7: 35900000000 | C7: 17900000000 | D7: Halved once the doubled total is fixed (5% x $358.8B).
A8: '1% efficiency gain' | B8: 7180000000 | C8: 3590000000 | D8: Same doubling.
A10: More important than the arithmetic: charges are list prices, not expected revenue, and Medicare pays a fixed DRG rate regardless of charges. v1's 'recovery' scenarios therefore described money that was never collectable. v2 replaces them with the one lever hospitals control - documentation of case severity.
